[{
    "id": 1,
    "Course": "HTML",
    "Instructor": "Kendall Clearley",
    "Price": 100,
    "Language": "Portuguese"
  }, {
    "id": 2,
    "Course": "HTML&CSS",
    "Instructor": "Bennett Rolfo",
    "Price": 200,
    "Language": "Polish"
  }, {
    "id": 3,
    "Course": "Master React js",
    "Instructor": "Karl Fairbanks",
    "Price": 125,
    "Language": "New Zealand Sign Language"
  }, {
    "id": 4,
    "Course": "Master Algorithms ",
    "Instructor": "Reeta Yurivtsev",
    "Price": 100,
    "Language": "Norwegian"
  }, {
    "id": 5,
    "Course": "Complete C guide",
    "Instructor": "Lucita Jenno",
    "Price": 90,
    "Language": "Swedish"
  }, {
    "id": 6,
    "Course": "Competitive Programming ",
    "Instructor": "Yuri Chilley",
    "Price": 200,
    "Language": "Persian"
  }, {
    "id": 7,
    "Course": "Discrete  Mathematics ",
    "Instructor": "Loren Hartness",
    "Price": 50,
    "Language": "Khmer"
  }, {
    "id": 8,
    "Course": "Arabic Language ",
    "Instructor": "Clifford Toomer",
    "Price": 80,
    "Language": "Arabic"
  }, {
    "id": 9,
    "Course": "Photoshop Master",
    "Instructor": "Abigael Matteotti",
    "Price": 90,
    "Language": "Guaraní"
  }, {
    "id": 10,
    "Course": "Web Security ",
    "Instructor": "Torr Lembke",
    "Price": 100,
    "Language": "Tamil"
  }, {
    "id": 11,
    "Course": "Spoken English",
    "Instructor": "Brande Bowart",
    "Price": 100,
    "Language": "English"
  }, {
    "id": 12,
    "Course": "Health HAcks",
    "Instructor": "Hartley Thiolier",
    "Price": 120,
    "Language": "English"
  }, {
    "id": 13,
    "Course": "Machine learning",
    "Instructor": "Vasili Grealey",
    "Price": 130,
    "Language": "English"
  }, {
    "id": 14,
    "Course": "Browsing in and out",
    "Instructor": "Anet Parkman",
    "Price": 140,
    "Language": "Hindi"
  }, {
    "id": 15,
    "Course": "Spanish Speaking",
    "Instructor": "Anabelle Ollive",
    "Price": 150,
    "Language": "Spanish"
  }, {
    "id": 16,
    "Course": "Arabic history",
    "Instructor": "Paulie Paskerful",
    "Price": 60,
    "Language": "Arabic"
  }, {
    "id": 17,
    "Course": "Javascript Mastery",
    "Instructor": "Jerrylee Beany",
    "Price": 170,
    "Language": "English"
  }, {
    "id": 18,
    "Course": "GRE In and out",
    "Instructor": "Blithe Seegar",
    "Price": 180,
    "Language": "English"
  }, {
    "id": 19,
    "Course": "Vue.js Beginner ",
    "Instructor": "Graig Lowing",
    "Price": 190,
    "Language": "English"
  }, {
    "id": 20,
    "Course": "Data Structure ",
    "Instructor": "Betta Togwell",
    "Price": 20,
    "Language": "English"
  }]